README.md
setup.py
baidu_d_tts/__init__.bak.py
baidu_d_tts/__init__.py
baidu_d_tts/baidu_ai_api.py
baidu_d_tts/baidu_client.py
baidu_d_tts/version.py
baidu_d_tts.egg-info/PKG-INFO
baidu_d_tts.egg-info/SOURCES.txt
baidu_d_tts.egg-info/dependency_links.txt
baidu_d_tts.egg-info/top_level.txt