Metadata-Version: 2.1
Name: baidu-d-tts
Version: 0.0.4
Summary: a pyttsx3 driver for baidu device, it use baidu.speech.tts.
Home-page: https://github.com/yumoqing/baidu_d_tts
Author: Yu Moqing
Author-email: yumoqing@gmail.com
Keywords: pyttsx,baidu,offline tts engine
Classifier: Intended Audience :: End Users/Desktop
Classifier: Intended Audience :: Developers
Classifier: Intended Audience :: Information Technology
Classifier: Intended Audience :: System Administrators
Classifier: Operating System :: OS Independent
Classifier: License :: OSI Approved :: Mozilla Public License 2.0 (MPL 2.0)
Classifier: Programming Language :: Python :: 3
